scrapylib/__init__.py
scrapylib/crawlera.py
scrapylib/deltafetch.py
scrapylib/guid.py
scrapylib/hcf.py
scrapylib/hubproxy.py
scrapylib/links.py
scrapylib/magicfields.py
scrapylib/pipelines.py
scrapylib/proxy.py
scrapylib/querycleaner.py
scrapylib/redisqueue.py
scrapylib/spidertrace.py
scrapylib/splitvariants.py
scrapylib/constraints/__init__.py
scrapylib/constraints/pipeline.py
scrapylib/processors/__init__.py
scrapylib/processors/date.py
scrapylib-1.7.1.dist-info/DESCRIPTION.rst
scrapylib-1.7.1.dist-info/METADATA
scrapylib-1.7.1.dist-info/RECORD
scrapylib-1.7.1.dist-info/WHEEL
scrapylib-1.7.1.dist-info/metadata.json
scrapylib-1.7.1.dist-info/top_level.txt
