Metadata-Version: 2.0
Name: scrapylib
Version: 1.7.1
Summary: Scrapy helper functions and processors
Home-page: https://pypi.python.org/pypi/scrapylib
Author: Scrapinghub
Author-email: info@scrapinghub.com
License: BSD
Platform: Any
Classifier: Development Status :: 7 - Inactive
Classifier: License :: OSI Approved :: BSD License
Classifier: Operating System :: OS Independent
Classifier: Programming Language :: Python
Classifier: Programming Language :: Python :: 2
Classifier: Programming Language :: Python :: 2.7
Classifier: Programming Language :: Python :: 2 :: Only
Requires-Dist: Scrapy (>=0.22.0)
